rslog/__init__.py
rslog/rslog.py
rslog/special_strings.py
rslog-0.1.8.dist-info/LICENSE
rslog-0.1.8.dist-info/METADATA
rslog-0.1.8.dist-info/WHEEL
rslog-0.1.8.dist-info/top_level.txt
rslog-0.1.8.dist-info/RECORD
