Metadata-Version: 2.2
Name: rslog
Version: 0.1.8
Summary: A simple, opinionated python library for logging locally. It will log a timestamp, the function name and add colors based on keywords in the log string that may indicate an error or warning.
Author-email: Rich Stokes <rich@rsmail.co>
License: MIT License
Project-URL: Homepage, https://github.com/richstokes/rslog
Keywords: logging,logger,python
Classifier: Programming Language :: Python :: 3
Classifier: License :: OSI Approved :: MIT License
Classifier: Operating System :: OS Independent
Requires-Python: >=3.7
License-File: LICENSE
